{
    "type": [
        
    ],
    "faq": [
        {
            "Sıra": 1,
            "TypeId": 1,
            "Soru (TR)": "BinBin Taksi Nedir?",
            "Cevap (TR)": "BinBin Taksi, yolcuların akıllı telefonları üzerinden kolayca taksi çağırmalarını sağlayan mobil uygulamadır. Uygulama sayesinde en yakın taksiye hızlı, güvenli ve pratik bir şekilde ulaşabilirsiniz.",
            "Soru (EN)": "What is BinBin Taxi?",
            "Cevap (EN)": "BinBin Taxi is a mobile application that allows passengers to easily call a taxi using their smartphones. You can reach the nearest taxi quickly, safely, and practically.",
            "Soru (BG)": null,
            "Cevap (BG)": null,
            "Soru (BS)": null,
            "Cevap (BS)": null,
            "Soru (RU)": null,
            "Cevap (RU)": null,
            "Soru (SQ)": null,
            "Cevap (SQ)": null,
            "Soru (MK)": null,
            "Cevap (MK)": null,
            "Soru (SR)": null,
            "Cevap (SR)": null,
            "Soru (HR)": null,
            "Cevap (HR)": null
        },
        {
            "Sıra": 2,
            "TypeId": 1,
            "Soru (TR)": "BinBin Taksi nerede kullanılabilir?",
            "Cevap (TR)": "Hizmet verdiğimiz şehirler için uygulamamızı inceleyebilir veya müşteri hizmetlerimizle iletişime geçebilirsiniz.",  
            "Soru (EN)": "Where can BinBin Taxi be used?",
            "Cevap (EN)": "You can review our application for the cities we serve or contact our customer service.",
            "Soru (BG)": null,
            "Cevap (BG)": null,
            "Soru (BS)": null,
            "Cevap (BS)": null,
            "Soru (RU)": null,
            "Cevap (RU)": null,
            "Soru (SQ)": null,
            "Cevap (SQ)": null,
            "Soru (MK)": null,
            "Cevap (MK)": null,
            "Soru (SR)": null,
            "Cevap (SR)": null,
            "Soru (HR)": null,
            "Cevap (HR)": null
        },
        {
            "Sıra": 3,
            "TypeId": 1,
            "Soru (TR)": "Nasıl taksi çağırabilirim?",
            "Cevap (TR)": "Uygulamaya kayıt olduktan sonra, gitmek istediğiniz konumu seçmelisiniz. Konumu seçtikten sonra ödeme yöntemini seçerek taksi çağırabilirsiniz.",
            "Soru (EN)": "How can I call/hail a taxi?",
            "Cevap (EN)": "After registering with the application, you must select your destination. After selecting the location, you can call a taxi by choosing the payment method.",
            "Soru (BG)": null,
            "Cevap (BG)": null,
            "Soru (BS)": null,
            "Cevap (BS)": null,
            "Soru (RU)": null,
            "Cevap (RU)": null,
            "Soru (SQ)": null,
            "Cevap (SQ)": null,
            "Soru (MK)": null,
            "Cevap (MK)": null,
            "Soru (SR)": null,
            "Cevap (SR)": null,
            "Soru (HR)": null,
            "Cevap (HR)": null
        },
        {
            "Sıra": 4,
            "TypeId": 1,
            "Soru (TR)": "Uygulama konumumu bulamıyor, ne yapmalıyım?",
            "Cevap (TR)": "Öncelikle telefonunuzun konum servislerinin açık olduğundan ve uygulamamıza gerekli izinleri verdiğinizden emin olun. Bulunduğunuz nokta alış adresi olarak otomatik olarak belirlenecek ve harita üzerinde konumu işaretlenecektir. Daha sonra bu adresi yazılı olarak veya haritadaki işaret üzerinden kolayca değiştirebilirsiniz.",
            "Soru (EN)": "The app cannot find my location, what should I do?",
            "Cevap (EN)": "First, make sure your phone's location services are on and that you have given the necessary permissions to our application. Your current location will be automatically determined as the pick-up address and marked on the map. You can then easily change this address either by typing it in or by adjusting the marker on the map.",
            "Soru (BG)": null,
            "Cevap (BG)": null,
            "Soru (BS)": null,
            "Cevap (BS)": null,
            "Soru (RU)": null,
            "Cevap (RU)": null,
            "Soru (SQ)": null,
            "Cevap (SQ)": null,
            "Soru (MK)": null,
            "Cevap (MK)": null
        },
        {
            "Sıra": 5,
            "TypeId": 1,
            "Soru (TR)": "Sürücü bilgilerimi görebilir mi?",
            "Cevap (TR)": "Sürücü, doğru yolcuyu aldığından emin olmak için yalnızca adınızı, soyadınızın ilk harfini ve taksi çağırdığınız konumu görebilir.",
            "Soru (EN)": "Can the driver see my information?",
            "Cevap (EN)": "The driver can only see your first name, the first letter of your last name, and the location you called the taxi from, to ensure they pick up the correct passenger.",
            "Soru (BG)": null,
            "Cevap (BG)": null,
            "Soru (BS)": null,
            "Cevap (BS)": null,
            "Soru (RU)": null,
            "Cevap (RU)": null,
            "Soru (SQ)": null,
            "Cevap (SQ)": null,
            "Soru (MK)": null,
            "Cevap (MK)": null
        },
        {
            "Sıra": 6,
            "TypeId": 1,
            "Soru (TR)": "Takside eşya unuttum, ne yapmalıyım?",
            "Cevap (TR)": "Bir eşyanızı unuttuysanız, durum tespiti ve yardım için hemen müşteri hizmetlerimize ulaşabilirsiniz. BinBin Taksi’de yaptığınız yolculukların detayları uygulamada kayıtlı olduğu için sürücüye ulaşmanız kolaylıkla sağlanır.",
            "Soru (EN)": "I forgot an item in the taxi, what should I do?",
            "Cevap (EN)": "If you have forgotten an item, you can immediately contact our customer service for assessment and assistance. Since the details of your trips with BinBin Taxi are recorded in the app, it is easily possible to reach the driver.",
            "Soru (BG)": null,
            "Cevap (BG)": null,
            "Soru (BS)": null,
            "Cevap (BS)": null,
            "Soru (RU)": null,
            "Cevap (RU)": null,
            "Soru (SQ)": null,
            "Cevap (SQ)": null,
            "Soru (MK)": null,
            "Cevap (MK)": null
        },
        {
            "Sıra": 7,
            "TypeId": 1,
            "Soru (TR)": "Sürücü veya yolculuğumla ilgili bir şikayetim/önerim var, ne yapabilirim?",
            "Cevap (TR)": "Yolculuğunuzla veya sürücünüzle ilgili tüm şikayet ve önerilerinizi müşteri hizmetleri kanallarımız aracılığıyla iletebilirsiniz.",
            "Soru (EN)": "I have a complaint/suggestion regarding the driver or my trip, what can I do?",
            "Cevap (EN)": "You can forward all your complaints and suggestions regarding your trip or driver through our customer service channels.",
            "Soru (BG)": null,
            "Cevap (BG)": null,
            "Soru (BS)": null,
            "Cevap (BS)": null,
            "Soru (RU)": null,
            "Cevap (RU)": null,
            "Soru (SQ)": null,
            "Cevap (SQ)": null,
            "Soru (MK)": null,
            "Cevap (MK)": null
        },
        {
            "Sıra": 8,
            "TypeId": 1,
            "Soru (TR)": "BinBin Taksi kullanımında ek bir ücretlendirme var mı?",
            "Cevap (TR)": "BinBin Taksi’de yolculuk sonunda taksimetrede yazan tutarı ve varsa yasal ek ücretleri (köprü, otoban, geçiş ücretleri) ödersiniz. Bunun dışında kalan ücretlendirme kalemleri için güncel hizmet koşulları geçerlidir.",
            "Soru (EN)": "Is there an additional fee for using BinBin Taxi?",
            "Cevap (EN)": "In BinBin Taxi, at the end of the trip, you pay the amount displayed on the taximeter and any legal extra charges (bridge, highway, toll fees). Current service terms apply for any additional pricing items such as service fee.",
            "Soru (BG)": null,
            "Cevap (BG)": null,
            "Soru (BS)": null,
            "Cevap (BS)": null,
            "Soru (RU)": null,
            "Cevap (RU)": null,
            "Soru (SQ)": null,
            "Cevap (SQ)": null,
            "Soru (MK)": null,
            "Cevap (MK)": null
        },
        {
            "Sıra": 9,
            "TypeId": 1,
            "Soru (TR)": "Sürücüler için ödeme yöntemim bir fark oluşturur mu?",
            "Cevap (TR)": "Hayır. Sürücüler için yolcunun nakit veya kartla ödeme yapması arasında herhangi bir fark yoktur.",
            "Soru (EN)": "Does my payment method make a difference for the drivers?",
            "Cevap (EN)": "No. For drivers, there is no difference between a passenger paying with cash or by card.",
            "Soru (BG)": null,
            "Cevap (BG)": null,
            "Soru (BS)": null,
            "Cevap (BS)": null,
            "Soru (RU)": null,
            "Cevap (RU)": null,
            "Soru (SQ)": null,
            "Cevap (SQ)": null,
            "Soru (MK)": null,
            "Cevap (MK)": null
        },
        {
            "Sıra": 10,
            "TypeId": 1,
            "Soru (TR)": "Uygulamaya birden fazla kartımı ekleyebilir miyim?",
            "Cevap (TR)": "BinBin Taksi uygulamasında herhangi bir kart sınırı yoktur. İstediğiniz kadar kart ekleyebilirsiniz.",
            "Soru (EN)": "Can I add more than one card to the app?",
            "Cevap (EN)": "There is no card limit in the BinBin Taxi application. You can add as many cards as you want.",
            "Soru (BG)": null,
            "Cevap (BG)": null,
            "Soru (BS)": null,
            "Cevap (BS)": null,
            "Soru (RU)": null,
            "Cevap (RU)": null,
            "Soru (SQ)": null,
            "Cevap (SQ)": null,
            "Soru (MK)": null,
            "Cevap (MK)": null
        },
        {
            "Sıra": 11,
            "TypeId": 1,
            "Soru (TR)": "Hangi ödeme yöntemleriyle taksi çağırabilirim?",
            "Cevap (TR)": "Ödeme yöntemlerini (nakit veya online ödeme) taksiyi çağırmadan hemen önce uygulama üzerinden seçebilirsiniz.",
            "Soru (EN)": "Which payment methods can I use to call a taxi?",
            "Cevap (EN)": "You can select the payment methods (cash or online payment) directly through the app right before calling the taxi. You can also change it in the end of the journey while in checkout process.",
            "Soru (BG)": null,
            "Cevap (BG)": null,
            "Soru (BS)": null,
            "Cevap (BS)": null,
            "Soru (RU)": null,
            "Cevap (RU)": null,
            "Soru (SQ)": null,
            "Cevap (SQ)": null,
            "Soru (MK)": null,
            "Cevap (MK)": null
        },
        {
            "Sıra": 12,
            "TypeId": 1,
            "Soru (TR)": "Taksiciye uygulama üzerinden bahşiş bırakabiliyor muyum?",
            "Cevap (TR)": "Evet, uygulamamızda taksi sürücüsüne bahşiş verme özelliği mevcuttur.",
            "Soru (EN)": "Can I leave a tip for the taxi driver through the app?",
            "Cevap (EN)": "Yes, the feature to give a tip to the taxi driver is available in our application.",
            "Soru (BG)": null,
            "Cevap (BG)": null,
            "Soru (BS)": null,
            "Cevap (BS)": null,
            "Soru (RU)": null,
            "Cevap (RU)": null,
            "Soru (SQ)": null,
            "Cevap (SQ)": null,
            "Soru (MK)": null,
            "Cevap (MK)": null
        },
        {
            "Sıra": 13,
            "TypeId": 1,
            "Soru (TR)": "Mükerrer ödeme durumunda ne yapmalıyım?",
            "Cevap (TR)": "Yolculuk sonunda yolculuk ücretini hem nakit hem de online ödeme olarak yaptıysanız müşteri hizmetlerimize ulaşabilirsiniz.",
            "Soru (EN)": "What should I do in case of a duplicate payment?",
            "Cevap (EN)": "If you have paid the trip fare both in cash and as an online payment at the end of the trip, you can contact our customer service.",
            "Soru (BG)": null,
            "Cevap (BG)": null,
            "Soru (BS)": null,
            "Cevap (BS)": null,
            "Soru (RU)": null,
            "Cevap (RU)": null,
            "Soru (SQ)": null,
            "Cevap (SQ)": null,
            "Soru (MK)": null,
            "Cevap (MK)": null
        },
        {
            "Sıra": 14,
            "TypeId": 1,
            "Soru (TR)": "Uygulamadan taksi çağırmaya çalışıyorum fakat taksi bulunamadı hatası alıyorum, sebebini öğrenebilir miyim?",
            "Cevap (TR)": "Şu an bölgesel nedenlerle müsait taksi bulunmamaktadır. Lütfen kısa bir süre bekleyerek tekrar taksi çağırmayı deneyiniz. Diğer servislerimizi kullanmayı da düşünebilirsiniz.",
            "Soru (EN)": "I am trying to call a taxi using the app but I am getting a \"taxi not found\" error, can I learn the reason?",
            "Cevap (EN)": "Currently, there might be no available taxis due to regional reasons. Please wait for a short while and try calling a taxi again. You may also consider using our other services.",
            "Soru (BG)": null,
            "Cevap (BG)": null,
            "Soru (BS)": null,
            "Cevap (BS)": null,
            "Soru (RU)": null,
            "Cevap (RU)": null,
            "Soru (SQ)": null,
            "Cevap (SQ)": null,
            "Soru (MK)": null,
            "Cevap (MK)": null
        }
    ]
}